{
    "name": "World 1",
    "created": "2.3.2021, 16:43:52",
    "height": 3,
    "width": 5,
    "tiles": [
        {
            "x": 0,
            "y": 0,
            "type": "wand",
            "signalcolor": "null",
            "cabletype": "notype",
            "rotation": "null",
            "speed": ""
        },
        {
            "x": 1,
            "y": 0,
            "type": "wand",
            "signalcolor": "null",
            "cabletype": "notype",
            "rotation": "null",
            "speed": ""
        },
        {
            "x": 2,
            "y": 0,
            "type": "wand",
            "signalcolor": "null",
            "cabletype": "notype",
            "rotation": "null",
            "speed": ""
        },
        {
            "x": 3,
            "y": 0,
            "type": "wand",
            "signalcolor": "null",
            "cabletype": "notype",
            "rotation": "null",
            "speed": ""
        },
        {
            "x": 4,
            "y": 0,
            "type": "wand",
            "signalcolor": "null",
            "cabletype": "notype",
            "rotation": "null",
            "speed": ""
        },
        {
            "x": 0,
            "y": 1,
            "type": "wand",
            "signalcolor": "null",
            "cabletype": "notype",
            "rotation": "null",
            "speed": ""
        },
        {
            "x": 4,
            "y": 1,
            "type": "wand",
            "signalcolor": "null",
            "cabletype": "notype",
            "rotation": "null",
            "speed": ""
        },
        {
            "x": 0,
            "y": 2,
            "type": "wand",
            "signalcolor": "null",
            "cabletype": "notype",
            "rotation": "null",
            "speed": ""
        },
        {
            "x": 4,
            "y": 2,
            "type": "wand",
            "signalcolor": "null",
            "cabletype": "notype",
            "rotation": "null",
            "speed": ""
        },
        {
            "x": 3,
            "y": 1,
            "type": "ende",
            "signalcolor": "null",
            "cabletype": "notype",
            "rotation": "null",
            "speed": ""
        }
    ],
    "entities": [
        {
            "type": "player",
            "x": 1,
            "y": 1,
            "rotation": "right"
        }
    ],
    "description": "Erste Welt, in der das Aufrufen der Methode zum Fortbewegen gezeigt wird."
}